pymob/__init__.py
pymob/__main__.py
pymob/infer.py
pymob/prior_predictive_checks.py
pymob/simulate.py
pymob/simulation.py
pymob/examples/__init__.py
pymob/examples/linear_regression.py
pymob/inference/__init__.py
pymob/inference/analysis.py
pymob/inference/base.py
pymob/inference/interactive.py
pymob/inference/numpyro_backend.py
pymob/inference/numpyro_dist_map.py
pymob/inference/optimization.py
pymob/inference/pyabc_backend.py
pymob/inference/pymoo_backend.py
pymob/inference/scipy_backend.py
pymob/inference/sbi/plot_posterior_predictions.py
pymob/inference/sbi/posterior_predictions.py
pymob/inference/sbi/process_simulations.py
pymob/inference/sbi/sbi_backend.py
pymob/inference/sbi/sbi_snle_sample_posterior.py
pymob/inference/sbi/sbi_utils.py
pymob/inference/sbi/train_network.py
pymob/sim/__init__.py
pymob/sim/base.py
pymob/sim/config.py
pymob/sim/evaluator.py
pymob/sim/parameters.py
pymob/sim/plot.py
pymob/sim/report.py
pymob/sim/solvetools.py
pymob/solvers/__init__.py
pymob/solvers/analytic.py
pymob/solvers/base.py
pymob/solvers/diffrax.py
pymob/solvers/scipy.py
pymob/solvers/symbolic.py
pymob/utils/__init__.py
pymob/utils/bayesian.py
pymob/utils/config.py
pymob/utils/errors.py
pymob/utils/help.py
pymob/utils/math_helpers.py
pymob/utils/misc.py
pymob/utils/plot_helpers.py
pymob/utils/store_file.py
pymob/utils/testing.py
pymob-0.6.4.dist-info/licenses/LICENSE
pymob-0.6.4.dist-info/METADATA
pymob-0.6.4.dist-info/WHEEL
pymob-0.6.4.dist-info/entry_points.txt
pymob-0.6.4.dist-info/top_level.txt
pymob-0.6.4.dist-info/RECORD
