Metadata-Version: 2.4
Name: pymob
Version: 0.6.4
Summary: Modelling platform for Python
Author-email: Florian Schunck <fluncki@protonmail.com>
License: MIT License
Project-URL: Homepage, https://github.com/flo-schu/pymob
Project-URL: Issue Tracker, https://github.com/flo-schu/pymob/issues
Classifier: Development Status :: 4 - Beta
Classifier: Programming Language :: Python :: 3
Classifier: Natural Language :: English
Classifier: License :: OSI Approved :: GNU General Public License v3 (GPLv3)
Classifier: Operating System :: OS Independent
Classifier: Topic :: Scientific/Engineering :: Bio-Informatics
Requires-Python: >=3.11
License-File: LICENSE
Requires-Dist: arviz<1.0.0,>=0.20
Requires-Dist: click<9.0.0,>=8.1.3
Requires-Dist: dpath<3.0.0,>=2.1.6
Requires-Dist: matplotlib<4.0.0,>=3.10.1
Requires-Dist: numpy<3.0.0,>=2.2.6
Requires-Dist: pandas<3.0.0,>=2.2.3
Requires-Dist: prettytable<4.0.0,>=3.7.0
Requires-Dist: scipy<2.0.0,>=1.15.3
Requires-Dist: scikit-learn<2.0.0,>=1.6.0
Requires-Dist: tqdm<5.0.0,>=4.65.0
Requires-Dist: xarray>=2025.4.0
Requires-Dist: sympy<2.0.0,>=1.12
Requires-Dist: pydantic<3.0.0,>=2.5.2
Requires-Dist: frozendict<3.0.0,>=2.3.10
Requires-Dist: numpydantic<2.0.0,>=1.3.3
Requires-Dist: Bottleneck<2.0.0,>=1.5.0
Requires-Dist: tabulate<1.0.0,>=0.9.0
Provides-Extra: dev
Requires-Dist: pytest>=7.3; extra == "dev"
Requires-Dist: pyinstrument>=4.5; extra == "dev"
Requires-Dist: bumpver; extra == "dev"
Requires-Dist: pre-commit; extra == "dev"
Requires-Dist: jupyter-core; extra == "dev"
Requires-Dist: nbconvert; extra == "dev"
Requires-Dist: jupytext; extra == "dev"
Requires-Dist: ipykernel; extra == "dev"
Requires-Dist: ipywidgets; extra == "dev"
Provides-Extra: docs
Requires-Dist: sphinx==7.2.6; extra == "docs"
Requires-Dist: myst-parser==2.0.0; extra == "docs"
Requires-Dist: sphinx-book-theme==1.1.0; extra == "docs"
Requires-Dist: pydata-sphinx-theme==0.15.1; extra == "docs"
Requires-Dist: sphinxcontrib-applehelp==1.0.8; extra == "docs"
Requires-Dist: sphinxcontrib-devhelp==1.0.6; extra == "docs"
Requires-Dist: sphinxcontrib-htmlhelp==2.0.5; extra == "docs"
Requires-Dist: sphinxcontrib-jsmath==1.0.1; extra == "docs"
Requires-Dist: sphinxcontrib-qthelp==1.0.7; extra == "docs"
Requires-Dist: sphinxcontrib-serializinghtml==1.1.10; extra == "docs"
Requires-Dist: myst-nb; extra == "docs"
Provides-Extra: pyabc
Requires-Dist: pyabc~=0.12.3; extra == "pyabc"
Requires-Dist: pathos~=0.3.1; extra == "pyabc"
Provides-Extra: numpyro
Requires-Dist: jax<1.0.0,>=0.6.1; extra == "numpyro"
Requires-Dist: jaxlib<1.0.0,>=0.6.1; extra == "numpyro"
Requires-Dist: diffrax<1.0.0,>=0.7.0; extra == "numpyro"
Requires-Dist: numpyro<1.0.0,>=0.18.0; extra == "numpyro"
Requires-Dist: equinox<1.0.0,>=0.12.2; extra == "numpyro"
Requires-Dist: optax<1.0.0,>=0.2.4; extra == "numpyro"
Requires-Dist: sympy2jax==0.0.5; extra == "numpyro"
Requires-Dist: graphviz; extra == "numpyro"
Provides-Extra: pymoo
Requires-Dist: pymoo~=0.6.0; extra == "pymoo"
Requires-Dist: pathos~=0.3.1; extra == "pymoo"
Provides-Extra: interactive
Requires-Dist: ipywidgets~=8.1.1; extra == "interactive"
Requires-Dist: IPython~=8.17.2; extra == "interactive"
Dynamic: license-file
